dynamallow/__init__.py
dynamallow/exceptions.py
dynamallow/local.py
dynamallow/model.py
dynamallow/table.py
dynamallow/types/__init__.py
dynamallow/types/_marshmallow.py
dynamallow/types/_schematics.py
dynamallow/types/base.py
dynamallow-0.0.3.dist-info/DESCRIPTION.rst
dynamallow-0.0.3.dist-info/METADATA
dynamallow-0.0.3.dist-info/RECORD
dynamallow-0.0.3.dist-info/WHEEL
dynamallow-0.0.3.dist-info/metadata.json
dynamallow-0.0.3.dist-info/top_level.txt
