Metadata-Version: 2.0
Name: dynamallow
Version: 0.0.3
Summary: Python ORM style interface to Amazon (AWS) DynamoDB using Schematics or Marshmallow for Schema validation
Home-page: https://github.com/borgstrom/dynamallow
Author: Evan Borgstrom
Author-email: evan@borgstrom.ca
License: Apache License Version 2.0
Platform: UNKNOWN
Classifier: Development Status :: 3 - Alpha
Classifier: Intended Audience :: Developers
Classifier: License :: OSI Approved :: Apache Software License
Classifier: Natural Language :: English
Classifier: Programming Language :: Python
Classifier: Topic :: Database
Classifier: Topic :: Internet
Classifier: Topic :: Software Development :: Libraries
Requires-Dist: boto3 (>=1.3,<1.4)
Requires-Dist: pytest (>=2.9,<3.0)
Requires-Dist: six
